Workbook

Sheet Databricks Master Syllabus
A1: Phase | B1: # | C1: Topic | D1: Learning Objective | E1: Success Criteria | F1: Est. Hours | G1: Guide Chapter | H1: Research Ref
A2: 1. Lakehouse & Platform Foundations | B2: 1 | C2: What a Lakehouse Is | D2: Understand how a lakehouse combines open files in cloud storage with warehouse-style tables, governance and one copy of data for batch, streaming, BI and ML. | E2: Explain in two minutes why a lakehouse avoids keeping a data lake and a warehouse in sync, using one example table. | F2: 2 | G2: 1 | H2: §13
A3: 1. Lakehouse & Platform Foundations | B3: 2 | C3: Control Plane vs Compute Plane on Azure | D3: Understand what runs in the Databricks account (control plane, serverless compute) and what runs in your Azure subscription (classic compute, workspace storage). | E3: Draw both planes for a classic and a serverless workload and say where each one's data and VMs live. | F3: 3 | G3: 1 | H3: §17
A4: 1. Lakehouse & Platform Foundations | B4: 3 | C4: Account, Workspace and Metastore | D4: Understand the account (identity, workspaces, metastores, billing), workspaces, and a Unity Catalog metastore shared by workspaces in one region. | E4: Given a two-region company, say how many metastores it needs and which workspaces attach to each. | F4: 2 | G4: 1 | H4: §17, §6.1
A5: 1. Lakehouse & Platform Foundations | B5: 4 | C5: Workspace Objects and Permissions | D5: Understand workspace-level assets (notebooks, folders, workspace files, jobs, pipelines, dashboards, queries) and that workspace access control lists, not Unity Catalog, govern them. | E5: Sort ten objects into Unity Catalog securables and workspace assets, and say who controls access to each. | F5: 1 | G5: 1 | H5: §6.1
A6: 1. Lakehouse & Platform Foundations | B6: 5 | C6: Product Names, Old and New | D6: Master the 2025-26 renames (DLT to Lakeflow Spark Declarative Pipelines, Asset Bundles to Declarative Automation Bundles, Delta Sharing to OpenSharing, APPLY CHANGES to AUTO CDC, Repos to Git folders). | E6: Translate five old product names from an older course into today's names without looking. | F6: 1 | G6: 1 | H6: §0
A7: 1. Lakehouse & Platform Foundations | B7: 6 | C7: Databricks Free Edition Setup | D7: Build a working Free Edition workspace for the hands-on steps, and know its limits (serverless only, no classic clusters or account console). | E7: Create a catalog, schema and table in Free Edition and list three things it cannot do. | F7: 2 | G7: 1 | H7: §18
A8: 2. Parquet: The File Format | B8: 7 | C8: Columnar Storage | D8: Understand why storing data column by column lets an engine read only the columns a query needs and compress similar values well. | E8: Explain, with a 3-column example, how many bytes a one-column query reads in row vs columnar storage. | F8: 2 | G8: 2 | H8: §22.1, §22.2
A9: 2. Parquet: The File Format | B9: 8 | C9: Parquet File Anatomy | D9: Master the layout of a Parquet file: PAR1 magic bytes, row groups, one column chunk per column, pages, and the footer written last. | E9: Sketch a Parquet file from memory and explain why the footer is written after the data and read first. | F9: 3 | G9: 2 | H9: §22.1
A10: 2. Parquet: The File Format | B10: 9 | C10: Statistics, Page Index and Bloom Filters | D10: Understand how min/max statistics, the optional page index and bloom filters let a reader skip data that cannot match a filter. | E10: For an equality filter on a high-cardinality ID column, say which of the three helps most and why. | F10: 3 | G10: 2 | H10: §22.2
A11: 2. Parquet: The File Format | B11: 10 | C11: Types, Encodings and Compression | D11: Understand physical vs logical types, nested data (definition and repetition levels), dictionary encoding and its fallback, and page compression codecs. | E11: Explain why a column with few distinct values compresses well and what happens when its dictionary grows too big. | F11: 3 | G11: 2 | H11: §22.3, §22.4
A12: 2. Parquet: The File Format | B12: 11 | C12: Parquet in Spark | D12: Understand Spark's Parquet behaviour: columns read as nullable, schema merging off by default, partition discovery, snappy as the default codec. | E12: Read a folder of Parquet files with two schemas in Free Edition and show the result with and without mergeSchema. | F12: 2 | G12: 2 | H12: §22.5
A13: 2. Parquet: The File Format | B13: 12 | C13: Hive-Style Partitioning and Small Files | D13: Understand Hive-style partition directories, why over-partitioning creates many small files, and why plain Parquet has no transactions. | E13: Explain to a stakeholder why a table partitioned by customer ID got slower, in three sentences. | F13: 2 | G13: 2 | H13: §22.5
... A108: 13. Production, Troubleshooting & Capstone | B108: 107 | C108: Testing Databricks Code | D108: Understand unit testing functions with pytest and SQL UDFs, kept outside notebooks in a Git folder. | E108: Write one pytest test for a transformation function and run it from a Git folder. | F108: 2 | G108: 24 | H108: §23.13
A109: 13. Production, Troubleshooting & Capstone | B109: 108 | C109: Capstone: End-to-End Medallion Pipeline | D109: Build a governed bronze-silver-gold pipeline with ingestion, expectations, a job, grants and monitoring. | E109: Run the pipeline in Free Edition, grant a reader group on gold, and explain every design choice to a reviewer. | F109: 10 | G109: 1-24 | H109: all
C110: TOTAL ESTIMATED HOURS | F110: =SUM(F2:F109) -> 254

Sheet Journey Progress Tracker
A1: Progress Summary
A2: Total Topics | B2: Completed | C2: In Progress | D2: Not Started | E2: % Complete
A3: =COUNTA(B6:B113) -> 108 | B3: =COUNTIF(D6:D113,"Completed") -> 0 | C3: =COUNTIF(D6:D113,"In Progress") -> 0 | D3: =COUNTIF(D6:D113,"Not Started") -> 108 | E3: =AVERAGE(E6:E113)/100 -> 0
A5: # | B5: Topic | C5: Phase | D5: Status | E5: Progress % | F5: Start Date | G5: Completion Date | H5: Evidence / Lab
A6: 1 | B6: ='Databricks Master Syllabus'!C2 -> What a Lakehouse Is | C6: ='Databricks Master Syllabus'!A2 -> 1. Lakehouse & Platform Foundations | D6: Not Started | E6: 0
A7: 2 | B7: ='Databricks Master Syllabus'!C3 -> Control Plane vs Compute Plane on Azure | C7: ='Databricks Master Syllabus'!A3 -> 1. Lakehouse & Platform Foundations | D7: Not Started | E7: 0
A8: 3 | B8: ='Databricks Master Syllabus'!C4 -> Account, Workspace and Metastore | C8: ='Databricks Master Syllabus'!A4 -> 1. Lakehouse & Platform Foundations | D8: Not Started | E8: 0
A9: 4 | B9: ='Databricks Master Syllabus'!C5 -> Workspace Objects and Permissions | C9: ='Databricks Master Syllabus'!A5 -> 1. Lakehouse & Platform Foundations | D9: Not Started | E9: 0
A10: 5 | B10: ='Databricks Master Syllabus'!C6 -> Product Names, Old and New | C10: ='Databricks Master Syllabus'!A6 -> 1. Lakehouse & Platform Foundations | D10: Not Started | E10: 0
A11: 6 | B11: ='Databricks Master Syllabus'!C7 -> Databricks Free Edition Setup | C11: ='Databricks Master Syllabus'!A7 -> 1. Lakehouse & Platform Foundations | D11: Not Started | E11: 0
A12: 7 | B12: ='Databricks Master Syllabus'!C8 -> Columnar Storage | C12: ='Databricks Master Syllabus'!A8 -> 2. Parquet: The File Format | D12: Not Started | E12: 0
A13: 8 | B13: ='Databricks Master Syllabus'!C9 -> Parquet File Anatomy | C13: ='Databricks Master Syllabus'!A9 -> 2. Parquet: The File Format | D13: Not Started | E13: 0
A14: 9 | B14: ='Databricks Master Syllabus'!C10 -> Statistics, Page Index and Bloom Filters | C14: ='Databricks Master Syllabus'!A10 -> 2. Parquet: The File Format | D14: Not Started | E14: 0
A15: 10 | B15: ='Databricks Master Syllabus'!C11 -> Types, Encodings and Compression | C15: ='Databricks Master Syllabus'!A11 -> 2. Parquet: The File Format | D15: Not Started | E15: 0
A16: 11 | B16: ='Databricks Master Syllabus'!C12 -> Parquet in Spark | C16: ='Databricks Master Syllabus'!A12 -> 2. Parquet: The File Format | D16: Not Started | E16: 0
A17: 12 | B17: ='Databricks Master Syllabus'!C13 -> Hive-Style Partitioning and Small Files | C17: ='Databricks Master Syllabus'!A13 -> 2. Parquet: The File Format | D17: Not Started | E17: 0
... A113: 108 | B113: ='Databricks Master Syllabus'!C109 -> Capstone: End-to-End Medallion Pipeline | C113: ='Databricks Master Syllabus'!A109 -> 13. Production, Troubleshooting & Capstone | D113: Not Started | E113: 0

Sheet Databricks Command Reference
A1: Category | B1: Databricks SQL | C1: Python / Databricks CLI
A2: Create a liquid-clustered Delta table | B2: CREATE TABLE t (id BIGINT, ts TIMESTAMP) CLUSTER BY (ts); | C2: df.write.clusterBy("ts").saveAsTable("t")
A3: See a table's history | B3: DESCRIBE HISTORY t; | C3: spark.sql("DESCRIBE HISTORY t")
A4: See a table's files, size and protocol | B4: DESCRIBE DETAIL t; | C4: spark.sql("DESCRIBE DETAIL t")
A5: Time travel | B5: SELECT * FROM t VERSION AS OF 3; | C5: spark.read.option("versionAsOf", 3).table("t")
A6: Restore a table | B6: RESTORE TABLE t TO VERSION AS OF 3; | C6: N/A - run the SQL with spark.sql()
A7: Preview and run VACUUM | B7: VACUUM t DRY RUN; then VACUUM t; | C7: N/A - run the SQL with spark.sql()
A8: Compact small files | B8: OPTIMIZE t; | C8: N/A - run the SQL with spark.sql()
A9: Upsert a batch | B9: MERGE INTO t USING s ON t.id = s.id WHEN MATCHED THEN UPDATE SET * WHEN NOT MATCHED THEN INSERT *; | C9: foreachBatch(fn) with MERGE inside fn for a stream
A10: Load files idempotently | B10: COPY INTO t FROM '/Volumes/c/s/v/in' FILEFORMAT = CSV; | C10: spark.readStream.format("cloudFiles").option("cloudFiles.format", "csv")
A11: Read files without a table | B11: SELECT * FROM read_files('/Volumes/c/s/v/in', format => 'parquet'); | C11: spark.read.format("parquet").load("/Volumes/c/s/v/in")
A12: Grant read on a schema | B12: GRANT USE CATALOG ON CATALOG c TO `analysts`; GRANT USE SCHEMA, SELECT ON SCHEMA c.s TO `analysts`; | C12: N/A - Catalog Explorer > Permissions tab
... A16: Deploy a bundle | B16: N/A - Databricks CLI | C16: databricks bundle validate; databricks bundle deploy -t dev; databricks bundle run <job>

Sheet Mental Model
A1: Concept | B1: Mental Model
A2: Parquet file | B2: A book whose table of contents is printed on the last page: you read the back first, then jump to the chapters you need.
A3: Row group | B3: A shelf of rows; each column of that shelf sits in its own box, so you can carry just one box.
A4: Delta transaction log | B4: The table's bank statement: data files are cash in a drawer, and only what the statement lists actually counts.
A5: Commit (version) | B5: One numbered line on that statement, added all at once or not at all.
A6: Tombstone | B6: A 'removed' note on a file that stays readable for a while so people mid-read aren't cut off.
A7: Checkpoint | B7: A running balance, so nobody has to add up every line since the account opened.
A8: Optimistic concurrency | B8: Everyone writes their draft at once; whoever submits second must check nothing they relied on has changed, or start again.
A9: VACUUM | B9: Shredding old statements' cash receipts: past the retention date, those versions can never be shown again.
A10: Time travel | B10: Asking the statement what the balance was on a past date, as long as the receipts haven't been shredded.
A11: Liquid clustering | B11: A librarian who keeps re-shelving books by the subjects people search for, without moving the whole library at once.
A12: Deletion vector | B12: Crossing a line out in pencil instead of reprinting the page; the reprint happens later.
... A16: Medallion architecture | B16: Ore, refined metal, finished jewellery: each stage is cleaner and closer to what the customer wants.

Sheet Error Catalogue
A1: Error Condition (SQLSTATE) | B1: What You See | C1: Likely Cause and Fix | D1: Taught In (#)
A2: TABLE_OR_VIEW_NOT_FOUND (42P01) | B2: The table or view can't be found | C2: Wrong name, wrong current schema, or no USE CATALOG/USE SCHEMA. Fix: Qualify catalog.schema.table; check grants. | D2: 38, 95
A3: SCHEMA_NOT_FOUND (42704) | B3: The schema can't be found | C3: Wrong name or catalog. Fix: Qualify the name with its catalog. | D3: 38
A4: UNRESOLVED_COLUMN (42703) | B4: A column or parameter can't be resolved | C4: Misspelt or missing column. Fix: Check the DataFrame's columns. | D4: 55
A5: INSUFFICIENT_PERMISSIONS (42501) | B5: Insufficient privileges | C5: A missing privilege in the USE CATALOG + USE SCHEMA + object chain. Fix: Grant the missing privilege. | D5: 42
A6: INSUFFICIENT_PERMISSIONS_EXT_LOC (42501) | B6: Insufficient privileges on an external location | C6: No privilege on the external location. Fix: Grant it on the external location. | D6: 41
A7: CAST_INVALID_INPUT (22018) | B7: A malformed value can't be cast | C7: Bad source data. Fix: Fix the data or type; try_cast returns NULL. | D7: 27
A8: DIVIDE_BY_ZERO (22012) | B8: Division by zero | C8: A zero divisor. Fix: try_divide returns NULL. | D8: 55
A9: DELTA_INSERT_COLUMN_ARITY_MISMATCH (42802) | B9: Target has N columns, the data has M | C9: Source and table schemas differ. Fix: Align columns or evolve the schema on purpose. | D9: 27, 96
A10: DELTA_FAILED_TO_MERGE_FIELDS (22005) | B10: Two field definitions can't be merged | C10: Type conflict during schema merge. Fix: Cast the source or change the table. | D10: 28, 96
A11: DELTA_MERGE_INCOMPATIBLE_DATATYPE (42K09) | B11: Incompatible data types can't be merged | C11: Type conflict. Fix: Cast the source or change the table. | D11: 28, 96
A12: DELTA_MULTIPLE_SOURCE_ROW_MATCHING_TARGET_ROW_IN_MERGE (21506) | B12: Several source rows match one target row | C12: Duplicate keys in the MERGE source. Fix: Deduplicate the source first. | D12: 29, 96
... A36: Out of memory after a stream restart | B36: The replanned micro-batch fails again | C36: The batch planned before the failure is too large. Fix: Scale up the compute to get past it. | D36: 91, 98
